{
	"info": {
		"_postman_id": "92254b48-7d9c-4180-a938-373ffa60ce4f",
		"name": "com.restful-booker.herokuapp.com",
		"schema": "https://schema.getpostman.com/json/collection/v2.1.0/collection.json",
		"_uid": "24041749-92254b48-7d9c-4180-a938-373ffa60ce4f"
	},
	"item": [
		{
			"name": "get",
			"item": [
				{
					"name": "https://restful-booker.herokuapp.com/booking/3",
					"event": [
						{
							"listen": "test",
							"script": {
								"id": "67fb3a87-3647-4f53-9781-735c13094506",
								"exec": [
									"pm.test(\"Status code is 200\", function () {\r",
									"    pm.response.to.have.status(200);\r",
									"});\r",
									"\r",
									""
								],
								"type": "text/javascript"
							}
						}
					],
					"id": "002e81e2-ce4c-4f02-b713-3ce39fc3688d",
					"protocolProfileBehavior": {
						"disableBodyPruning": true
					},
					"request": {
						"method": "GET",
						"header": [],
						"url": {
							"raw": "https://restful-booker.herokuapp.com/booking/3",
							"protocol": "https",
							"host": [
								"restful-booker",
								"herokuapp",
								"com"
							],
							"path": [
								"booking",
								"3"
							]
						}
					},
					"response": []
				},
				{
					"name": "https://restful-booker.herokuapp.com/booking/5",
					"event": [
						{
							"listen": "test",
							"script": {
								"id": "371f04f3-15df-4b77-85d9-90f06c8c2218",
								"exec": [
									"pm.test(\"Status code is 200\", function () {\r",
									"    pm.response.to.have.status(200);\r",
									"});\r",
									"\r",
									"pm.test(\"Body matches Mark\", function () {\r",
									"    pm.expect(pm.response.text()).to.include(\"Mark\");\r",
									"});"
								],
								"type": "text/javascript"
							}
						}
					],
					"id": "3a2447ed-ca2a-478c-bc8c-8a32fe43ad88",
					"protocolProfileBehavior": {
						"disableBodyPruning": true
					},
					"request": {
						"method": "GET",
						"header": [],
						"url": {
							"raw": "https://restful-booker.herokuapp.com/booking/5",
							"protocol": "https",
							"host": [
								"restful-booker",
								"herokuapp",
								"com"
							],
							"path": [
								"booking",
								"5"
							]
						}
					},
					"response": []
				},
				{
					"name": "https://restful-booker.herokuapp.com/booking/7",
					"event": [
						{
							"listen": "test",
							"script": {
								"id": "4d511f77-939e-4751-800a-ed0b9d98c463",
								"exec": [
									"pm.test(\"Status code is 200\", function () {\r",
									"    pm.response.to.have.status(200);\r",
									"});\r",
									"\r",
									"pm.test(\"Body matches Sally\", function () {\r",
									"    pm.expect(pm.response.text()).to.include(\"Sally\");\r",
									"});\r",
									"pm.test(\"Body matches Jackson\", function () {\r",
									"    pm.expect(pm.response.text()).to.include(\"Jackson\");\r",
									"});\r",
									"pm.test(\"Body matches checkin\", function () {\r",
									"    pm.expect(pm.response.text()).to.include(\"2021-09-27\");\r",
									"});\r",
									"pm.test(\"Body matches checkout\", function () {\r",
									"    pm.expect(pm.response.text()).to.include(\"2021-10-29\");\r",
									"});\r",
									""
								],
								"type": "text/javascript"
							}
						}
					],
					"id": "3a9e7b6d-82e5-4f6a-94b9-efeb5402cd7e",
					"protocolProfileBehavior": {
						"disableBodyPruning": true
					},
					"request": {
						"method": "GET",
						"header": [],
						"url": {
							"raw": "https://restful-booker.herokuapp.com/booking/7",
							"protocol": "https",
							"host": [
								"restful-booker",
								"herokuapp",
								"com"
							],
							"path": [
								"booking",
								"7"
							]
						}
					},
					"response": []
				},
				{
					"name": "https://restful-booker.herokuapp.com/booking/7",
					"event": [
						{
							"listen": "test",
							"script": {
								"id": "4d511f77-939e-4751-800a-ed0b9d98c463",
								"exec": [
									"pm.test(\"Status code is 200\", function () {\r",
									"    pm.response.to.have.status(200);\r",
									"});\r",
									"\r",
									"pm.test(\"Body matches Eric\", function () {\r",
									"    pm.expect(pm.response.text()).to.include(\"Eric\");\r",
									"});\r",
									"pm.test(\"Body matches Smith\", function () {\r",
									"    pm.expect(pm.response.text()).to.include(\"Smith\");\r",
									"});\r",
									"pm.test(\"Body matches checkin\", function () {\r",
									"    pm.expect(pm.response.text()).to.include(\"2017-01-08\");\r",
									"});\r",
									""
								],
								"type": "text/javascript"
							}
						}
					],
					"id": "15ffd073-62b8-44f4-a6d9-7829c2282f88",
					"protocolProfileBehavior": {
						"disableBodyPruning": true
					},
					"request": {
						"method": "GET",
						"header": [],
						"url": {
							"raw": "https://restful-booker.herokuapp.com/booking/7",
							"protocol": "https",
							"host": [
								"restful-booker",
								"herokuapp",
								"com"
							],
							"path": [
								"booking",
								"7"
							]
						}
					},
					"response": []
				}
			],
			"id": "ada3019e-0375-4179-becc-c5583657b895"
		},
		{
			"name": "post",
			"item": [
				{
					"name": "https://restful-booker.herokuapp.com/booking",
					"id": "ff1a8c4c-32aa-4293-a592-853679be163f",
					"protocolProfileBehavior": {
						"disableBodyPruning": true
					},
					"request": {
						"method": "POST",
						"header": [],
						"body": {
							"mode": "raw",
							"raw": "{\r\n    \"username\" : \"admin\",\r\n    \"password\" : \"password123\"\r\n}",
							"options": {
								"raw": {
									"language": "json"
								}
							}
						},
						"url": {
							"raw": "https://restful-booker.herokuapp.com/auth",
							"protocol": "https",
							"host": [
								"restful-booker",
								"herokuapp",
								"com"
							],
							"path": [
								"auth"
							]
						}
					},
					"response": []
				}
			],
			"id": "4a7ea8d7-eead-42da-b753-c5108e03192a"
		}
	]
}